lmbench/cli.py
lmbench-0.1.1.dist-info/licenses/LICENSE
lmbench-0.1.1.dist-info/METADATA
lmbench-0.1.1.dist-info/WHEEL
lmbench-0.1.1.dist-info/entry_points.txt
lmbench-0.1.1.dist-info/top_level.txt
lmbench-0.1.1.dist-info/RECORD
