Metadata-Version: 2.4
Name: lmbench
Version: 0.1.1
Summary: Benchmark your device's LLM training power
Requires-Python: >=3.8
License-File: LICENSE
Requires-Dist: torch
Dynamic: license-file
